README.rst
setup.cfg
setup.py
aliyun_python_sdk_asapi.egg-info/PKG-INFO
aliyun_python_sdk_asapi.egg-info/SOURCES.txt
aliyun_python_sdk_asapi.egg-info/dependency_links.txt
aliyun_python_sdk_asapi.egg-info/requires.txt
aliyun_python_sdk_asapi.egg-info/top_level.txt
aliyunsdkasapi/ASClient.py
aliyunsdkasapi/AsapiRequest.py
aliyunsdkasapi/__init__.py
aliyunsdkasapi/client.py
aliyunsdkasapi/request.py
aliyunsdkasapi/request_interceptor.py
aliyunsdkasapi/auth/__init__.py
aliyunsdkasapi/auth/composer/__init__.py
aliyunsdkasapi/auth/composer/rpc_signature_composer.py
aliyunsdkasapi/auth/composer/sha_hmac256.py
aliyunsdkasapi/auth/composer/sm3_hmac.py
aliyunsdkasapi/http/__init__.py
aliyunsdkasapi/http/http_response.py