Metadata-Version: 1.1
Name: aliyun-python-sdk-asapi
Version: 2.4.7.2
Summary: The asapi module of Aliyun ApsaraStack Python sdk.
Home-page: https://www.aliyun.com/product/apsara-stack
Author: Aliyun
Author-email: UNKNOWN
License: Apache
Keywords: aliyun,sdk,asapi
Platform: any
Classifier: Development Status :: 4 - Beta
Classifier: Intended Audience :: Developers
Classifier: License :: OSI Approved :: Apache Software License
Classifier: Programming Language :: Python
Classifier: Programming Language :: Python :: 2.6
Classifier: Programming Language :: Python :: 2.7
Classifier: Programming Language :: Python :: 3
Classifier: Programming Language :: Python :: 3.3
Classifier: Programming Language :: Python :: 3.4
Classifier: Programming Language :: Python :: 3.5
Classifier: Programming Language :: Python :: 3.6
Classifier: Programming Language :: Python :: 3.7
Classifier: Topic :: Software Development
